bitbanker_sdk/__init__.py
bitbanker_sdk/clients.py
bitbanker_sdk/dto.py
bitbanker_sdk/types_.py
bitbanker_sdk/utils.py
bitbanker_sdk-0.0.2.dist-info/LICENSE
bitbanker_sdk-0.0.2.dist-info/WHEEL
bitbanker_sdk-0.0.2.dist-info/METADATA
bitbanker_sdk-0.0.2.dist-info/RECORD
