Metadata-Version: 2.1
Name: bitbanker-sdk
Version: 0.0.2
Summary: Bitbanker.org API client
Home-page: https://github.com/melnikovsa/python-bitbanker-sdk
Author: Evgeny Solomatin
Author-email: solgenya@gmail.com
Requires-Python: >=3.7.0,<4.0.0
Classifier: Programming Language :: Python :: 3
Classifier: Programming Language :: Python :: 3.10
Classifier: Programming Language :: Python :: 3.7
Classifier: Programming Language :: Python :: 3.8
Classifier: Programming Language :: Python :: 3.9
Requires-Dist: httpx (>=0.22.0,<0.23.0)
Requires-Dist: pydantic (>=1.9.0,<2.0.0)
Project-URL: Repository, https://github.com/melnikovsa/python-bitbanker-sdk
